{"responses":{"200":{"description":"Example response","content":{"application/json":{"schema":{"type":"array","items":{"description":"The company attachment","type":"object","x-examples":{"success_status":{"uuid":"1263eae5-4411-48d9-bd6d-18ed93082e65","name":"Company_Attachment_File.pdf","category":"gep_notice","upload_time":"2024-09-10T01:54:20Z"}},"x-tags":["Company Attachment"],"properties":{"uuid":{"type":"string","description":"UUID of the company attachment"},"name":{"type":"string","description":"name of the file uploaded"},"category":{"type":"string","description":"The category of the company attachment","enum":["gep_notice","compliance","other"]},"upload_time":{"type":"string","description":"The ISO 8601 timestamp of when an attachment was uploaded"}},"title":"Company-Attachment"}},"examples":{"Example":{"value":[{"uuid":"5de11791-98fd-4587-9ed0-d5d804b8e647","name":"Company_Attachment_File1.pdf","category":"gep_notice","upload_time":"2022-02-01T00:00:00.000Z"},{"uuid":"987058cc-23ee-46e9-81ef-5cee086cceca","name":"Company_Attachment_File2.pdf","category":"gep_notice","upload_time":"2022-02-01T00:00:00.000Z"}]}}}}},"404":{"description":"Not Found \n  \nThe requested resource does not exist. Make sure the provided UUID is valid.\n"}}}