{"parameters":[{"name":"company_id","in":"path","required":true,"schema":{"type":"string"},"description":"The UUID of the company"},{"name":"sort_by","in":"query","required":false,"description":"Sort company forms. Options: name, year, quarter, draft, document_content_type, created_at (optionally with :asc or :desc suffix)","schema":{"type":"string","pattern":"^(name|year|quarter|draft|document_content_type|created_at)(:(asc|desc))?$"}},{"name":"X-Gusto-API-Version","in":"header","required":false,"description":"Determines the date-based API version associated with your API call. If none is provided, your application's [minimum API version](https://docs.gusto.com/embedded-payroll/docs/api-versioning#minimum-api-version) is used.","schema":{"type":"string","enum":["2025-06-15"],"default":"2025-06-15"}}]}