{"title":"Body","body":{"required":true,"content":{"application/json":{"schema":{"type":"object","properties":{"version":{"type":"string","description":"The current version of the object. See the [versioning guide](https://docs.gusto.com/embedded-payroll/docs/versioning#object-layer) for information on how to use this field.","example":"56a489ce86ed6c1b0f0cecc4050a0b01"},"filing_status":{"type":"string","enum":["Single","Married","Head of Household","Exempt from withholding"],"description":"Determines which tax return form an individual will use. One of: Single, Married, Head of Household, Exempt from withholding.","example":"Single"},"extra_withholding":{"type":"number","description":"Additional amount to be withheld from each paycheck."},"two_jobs":{"type":"boolean","description":"If there are only two jobs (e.g., you and your spouse each have a job), set to true."},"dependents_amount":{"type":"number","description":"Amount for dependents; a dependent entitles the taxpayer to claim a dependency exemption."},"other_income":{"type":"number","description":"Other income amount."},"deductions":{"type":"number","description":"Deductions other than the standard deduction to reduce withholding."},"w4_data_type":{"type":"string","enum":["rev_2020_w4"],"description":"The version of the W4 form. Only rev_2020_w4 is accepted for updates."},"federal_withholding_allowance":{"type":"integer","description":"Only applicable when w4_data_type is 'pre_2020_w4' (pre-2020 W4 forms are deprecated for updates)."},"additional_withholding":{"type":"number","description":"Only applicable when w4_data_type is 'pre_2020_w4' (pre-2020 W4 forms are deprecated for updates)."}},"required":["version","w4_data_type","filing_status"]}}}}}